LICENSE
MANIFEST.in
README.md
setup.py
django_preserialize.egg-info/PKG-INFO
django_preserialize.egg-info/SOURCES.txt
django_preserialize.egg-info/dependency_links.txt
django_preserialize.egg-info/pbr.json
django_preserialize.egg-info/requires.txt
django_preserialize.egg-info/top_level.txt
preserialize/__init__.py
preserialize/serialize.py
preserialize/utils.py