Metadata-Version: 1.1
Name: django-preserialize
Version: 1.2.1
Summary: Pre-serialize model instances and querysets
Home-page: https://github.com/bruth/django-preserialize/
Author: Byron Ruth
Author-email: b@devel.io
License: BSD
Keywords: serialize model queryset django
Platform: UNKNOWN
Classifier: Development Status :: 5 - Production/Stable
Classifier: License :: OSI Approved :: BSD License
Classifier: Programming Language :: Python :: 2.6
Classifier: Programming Language :: Python :: 2.7
Classifier: Programming Language :: Python :: 3.3
Classifier: Programming Language :: Python :: 3.4
Classifier: Programming Language :: Python :: 3.5
